Metadata-Version: 2.1
Name: odoo-addon-partner_manual_rank
Version: 19.0.1.0.0.2
Requires-Dist: odoo==19.0.*
Summary: Be able to manually flag partners as customer or supplier.
Home-page: https://github.com/OCA/partner-contact
License: AGPL-3
Author: ForgeFlow, Vauxoo, Odoo Community Association (OCA)
Author-email: support@odoo-community.org
Classifier: Programming Language :: Python
Classifier: Framework :: Odoo
Classifier: Framework :: Odoo :: 19.0
Classifier: License :: OSI Approved :: GNU Affero General Public License v3
